setup.py
number2name_es/__init__.py
number2name_es/main.py
number2name_es/nombre_numero.py
number2name_es.egg-info/PKG-INFO
number2name_es.egg-info/SOURCES.txt
number2name_es.egg-info/dependency_links.txt
number2name_es.egg-info/requires.txt
number2name_es.egg-info/top_level.txt