Metadata-Version: 1.1
Name: number2name-es
Version: 1.0.0
Summary: Transform numbers digits to numbers in words
Home-page: https://github.com/dpineiden/number2name
Author: David Pineda Osorio
Author-email: dahalpi@gmail.com
License: MIT
Keywords: numbers words
Platform: UNKNOWN
Classifier: Development Status :: 4 - Beta
Classifier: License :: OSI Approved :: MIT License
Classifier: License :: OSI Approved :: MIT License
